<!DOCTYPE keyboard SYSTEM "../dtd/ldmlKeyboard.dtd">
<keyboard locale="lt-LT-t-k0-linux-ratise">
  <version platform="0" number="$Revision$"/>
  <names>
    <name value="Lithuanian (Ratise)"/>
    <name value="lt(ratise)"/>
  </names>
  <settings transformFailure="omit" transformPartial="hide"/>
  <keyMap>
    <map iso="E00" to="+"/>
    <map iso="E01" to="!"/>
    <map iso="E02" to=":"/>
    <map iso="E03" to="."/>
    <map iso="E04" to="*"/>
    <map iso="E05" to="_"/>
    <map iso="E06" to="—"/>
    <map iso="E07" to="="/>
    <map iso="E08" to=","/>
    <map iso="E09" to=";"/>
    <map iso="E10" to="/"/>
    <map iso="E11" to="w"/>
    <map iso="E12" to="?"/>
    <map iso="D01" to="ū"/>
    <map iso="D02" to="ė"/>
    <map iso="D03" to="y"/>
    <map iso="D04" to="o"/>
    <map iso="D05" to="q"/>
    <map iso="D06" to="j"/>
    <map iso="D07" to="n"/>
    <map iso="D08" to="k"/>
    <map iso="D09" to="g"/>
    <map iso="D10" to="b"/>
    <map iso="D11" to="c"/>
    <map iso="D12" to="f"/>
    <map iso="C01" to="u"/>
    <map iso="C02" to="e"/>
    <map iso="C03" to="i"/>
    <map iso="C04" to="a"/>
    <map iso="C05" to="h"/>
    <map iso="C06" to="l"/>
    <map iso="C07" to="r"/>
    <map iso="C08" to="t"/>
    <map iso="C09" to="s"/>
    <map iso="C10" to="p"/>
    <map iso="C11" to="ž"/>
    <map iso="C12" to="z"/>
    <map iso="B00" to="-"/>
    <map iso="B01" to="ų"/>
    <map iso="B02" to="ę"/>
    <map iso="B03" to="į"/>
    <map iso="B04" to="ą"/>
    <map iso="B05" to="x"/>
    <map iso="B06" to="v"/>
    <map iso="B07" to="m"/>
    <map iso="B08" to="d"/>
    <map iso="B09" to="š"/>
    <map iso="B10" to="č"/>
    <map iso="A03" to=" "/>
  </keyMap>
  <keyMap modifiers="shift">
    <map iso="E00" to="§"/>
    <map iso="E01" to="¤"/>
    <map iso="E02" to="@"/>
    <map iso="E03" to="#"/>
    <map iso="E04" to="$"/>
    <map iso="E05" to="%"/>
    <map iso="E06" to="|"/>
    <map iso="E07" to="&amp;"/>
    <map iso="E08" to="&lt;"/>
    <map iso="E09" to="&gt;"/>
    <map iso="E10" to="\"/>
    <map iso="E11" to="W"/>
    <map iso="E12" to="~"/>
    <map iso="D01" to="Ū"/>
    <map iso="D02" to="Ė"/>
    <map iso="D03" to="Y"/>
    <map iso="D04" to="O"/>
    <map iso="D05" to="Q"/>
    <map iso="D06" to="J"/>
    <map iso="D07" to="N"/>
    <map iso="D08" to="K"/>
    <map iso="D09" to="G"/>
    <map iso="D10" to="B"/>
    <map iso="D11" to="C"/>
    <map iso="D12" to="F"/>
    <map iso="C01" to="U"/>
    <map iso="C02" to="E"/>
    <map iso="C03" to="I"/>
    <map iso="C04" to="A"/>
    <map iso="C05" to="H"/>
    <map iso="C06" to="L"/>
    <map iso="C07" to="R"/>
    <map iso="C08" to="T"/>
    <map iso="C09" to="S"/>
    <map iso="C10" to="P"/>
    <map iso="C11" to="Ž"/>
    <map iso="C12" to="Z"/>
    <map iso="B00" to="–"/>
    <map iso="B01" to="Ų"/>
    <map iso="B02" to="Ę"/>
    <map iso="B03" to="Į"/>
    <map iso="B04" to="Ą"/>
    <map iso="B05" to="X"/>
    <map iso="B06" to="V"/>
    <map iso="B07" to="M"/>
    <map iso="B08" to="D"/>
    <map iso="B09" to="Š"/>
    <map iso="B10" to="Č"/>
    <map iso="A03" to=" "/>
  </keyMap>
  <keyMap modifiers="altR">
    <map iso="E00" to="`"/>
    <map iso="E01" to="’"/>
    <map iso="E02" to="⟨"/>
    <map iso="E03" to="⟩"/>
    <map iso="E04" to="”"/>
    <map iso="E05" to="…"/>
    <map iso="E06" to="^"/>
    <map iso="E07" to="7"/>
    <map iso="E08" to="8"/>
    <map iso="E09" to="9"/>
    <map iso="E10" to="÷"/>
    <map iso="E11" to="Ω"/>
    <map iso="E12" to="≈"/>
    <map iso="D01" to="‘"/>
    <map iso="D02" to="["/>
    <map iso="D03" to="]"/>
    <map iso="D04" to="“"/>
    <map iso="D05" to="́"/>
    <map iso="D06" to="€"/>
    <map iso="D07" to="4"/>
    <map iso="D08" to="5"/>
    <map iso="D09" to="6"/>
    <map iso="D10" to="×"/>
    <map iso="D11" to="¢"/>
    <map iso="D12" to="⁄"/>
    <map iso="C01" to="'"/>
    <map iso="C02" to="("/>
    <map iso="C03" to=")"/>
    <map iso="C04" to="&quot;"/>
    <map iso="C05" to="̃"/>
    <map iso="C06" to="ł"/>
    <map iso="C07" to="1"/>
    <map iso="C08" to="2"/>
    <map iso="C09" to="3"/>
    <map iso="C10" to="−"/>
    <map iso="C11" to="-"/>
    <map iso="C12" to="°"/>
    <map iso="B00" to="̇"/>
    <map iso="B01" to="‚"/>
    <map iso="B02" to="{"/>
    <map iso="B03" to="}"/>
    <map iso="B04" to="„"/>
    <map iso="B05" to="̀"/>
    <map iso="B06" to="√"/>
    <map iso="B07" to="0"/>
    <map iso="B08" to="."/>
    <map iso="B09" to=","/>
    <map iso="B10" to="+"/>
    <map iso="A03" to=" "/>
  </keyMap>
  <keyMap modifiers="altR+shift">
    <map iso="E00" to="´"/>
    <map iso="E01" to="¡"/>
    <map iso="E02" to="←"/>
    <map iso="E03" to="→"/>
    <map iso="E04" to="£"/>
    <map iso="E05" to="‰"/>
    <map iso="E06" to="¦"/>
    <map iso="E07" to="≠"/>
    <map iso="E08" to="≤"/>
    <map iso="E09" to="≥"/>
    <map iso="E10" to="‖"/>
    <map iso="E11" to="ß"/>
    <map iso="E12" to="¿"/>
    <map iso="D01" to="›"/>
    <map iso="D02" to="\u{030a}"/>
    <map iso="D03" to="\u{0302}"/>
    <map iso="D04" to="»"/>
    <map iso="D05" to="↑"/>
    <map iso="D06" to="¥"/>
    <map iso="D07" to="¬"/>
    <map iso="D08" to="†"/>
    <map iso="D09" to="•"/>
    <map iso="D10" to="∞"/>
    <map iso="D11" to="©"/>
    <map iso="D12" to="™"/>
    <map iso="C01" to="\u{0304}"/>
    <map iso="C02" to="\u{0300}"/>
    <map iso="C03" to="\u{0301}"/>
    <map iso="C04" to="\u{0308}"/>
    <map iso="C05" to="\u{0303}"/>
    <map iso="C06" to="Ł"/>
    <map iso="C07" to="¹"/>
    <map iso="C08" to="²"/>
    <map iso="C09" to="³"/>
    <map iso="C10" to="¶"/>
    <map iso="C11" to="\u{0327}"/>
    <map iso="C12" to="®"/>
    <map iso="B00" to="‑"/>
    <map iso="B01" to="‹"/>
    <map iso="B02" to="\u{0306}"/>
    <map iso="B03" to="\u{030c}"/>
    <map iso="B04" to="«"/>
    <map iso="B05" to="↓"/>
    <map iso="B06" to="◊"/>
    <map iso="B07" to="µ"/>
    <map iso="B08" to="‡"/>
    <map iso="B09" to="·"/>
    <map iso="B10" to="±"/>
    <map iso="A03" to=" "/>
  </keyMap>
  <transforms type="simple">
    <transform from="\u{0303} " to="~"/>
    <transform from="\u{0303}\u{0303}" to="~"/>
    <transform from="\u{0301} " to="'"/>
    <transform from="\u{0301}\u{0301}" to="´"/>
    <transform from="\u{0300} " to="`"/>
    <transform from="\u{0300}\u{0300}" to="`"/>
    <transform from="\u{0302} " to="^"/>
    <transform from="\u{0302}\u{0302}" to="^"/>
    <transform from="\u{030a} " to="°"/>
    <transform from="\u{030a}\u{030a}" to="°"/>
    <transform from="\u{0304} " to="¯"/>
    <transform from="\u{0304}\u{0304}" to="¯"/>
    <transform from="\u{0306} " to="˘"/>
    <transform from="\u{0306}\u{0306}" to="˘"/>
    <transform from="\u{0308}\u{0308}" to="¨"/>
    <transform from="\u{0308} " to="&quot;"/>
    <transform from="\u{030c} " to="ˇ"/>
    <transform from="\u{030c}\u{030c}" to="ˇ"/>
    <transform from="\u{0327} " to="¸"/>
    <transform from="\u{0327}\u{0327}" to="¸"/>
    <transform from="\u{0302}2" to="²"/>
    <transform from="\u{0302}3" to="³"/>
    <transform from="\u{0302}1" to="¹"/>
    <transform from="\u{0300}A" to="À"/>
    <transform from="\u{0301}A" to="Á"/>
    <transform from="\u{0302}A" to="Â"/>
    <transform from="\u{0303}A" to="Ã"/>
    <transform from="\u{0308}A" to="Ä"/>
    <transform from="\u{030a}A" to="Å"/>
    <transform from="\u{0327}C" to="Ç"/>
    <transform from="\u{0300}E" to="È"/>
    <transform from="\u{0301}E" to="É"/>
    <transform from="\u{0302}E" to="Ê"/>
    <transform from="\u{0308}E" to="Ë"/>
    <transform from="\u{0300}I" to="Ì"/>
    <transform from="\u{0301}I" to="Í"/>
    <transform from="\u{0302}I" to="Î"/>
    <transform from="\u{0308}I" to="Ï"/>
    <transform from="\u{0301}J" to="J"/>
    <transform from="\u{0303}N" to="Ñ"/>
    <transform from="\u{0300}O" to="Ò"/>
    <transform from="\u{0301}O" to="Ó"/>
    <transform from="\u{0302}O" to="Ô"/>
    <transform from="\u{0303}O" to="Õ"/>
    <transform from="\u{0308}O" to="Ö"/>
    <transform from="\u{0300}U" to="Ù"/>
    <transform from="\u{0301}U" to="Ú"/>
    <transform from="\u{0302}U" to="Û"/>
    <transform from="\u{0308}U" to="Ü"/>
    <transform from="\u{0301}Y" to="Ý"/>
    <transform from="\u{0300}a" to="à"/>
    <transform from="\u{0301}a" to="á"/>
    <transform from="\u{0302}a" to="â"/>
    <transform from="\u{0303}a" to="ã"/>
    <transform from="\u{0308}a" to="ä"/>
    <transform from="\u{030a}a" to="å"/>
    <transform from="\u{0327}c" to="ç"/>
    <transform from="\u{0300}e" to="è"/>
    <transform from="\u{0301}e" to="é"/>
    <transform from="\u{0302}e" to="ê"/>
    <transform from="\u{0308}e" to="ë"/>
    <transform from="\u{0300}i" to="ì"/>
    <transform from="\u{0301}i" to="í"/>
    <transform from="\u{0302}i" to="î"/>
    <transform from="\u{0308}i" to="ï"/>
    <transform from="\u{0301}j" to="j"/>
    <transform from="\u{0303}n" to="ñ"/>
    <transform from="\u{0300}o" to="ò"/>
    <transform from="\u{0301}o" to="ó"/>
    <transform from="\u{0302}o" to="ô"/>
    <transform from="\u{0303}o" to="õ"/>
    <transform from="\u{0308}o" to="ö"/>
    <transform from="\u{0300}u" to="ù"/>
    <transform from="\u{0301}u" to="ú"/>
    <transform from="\u{0302}u" to="û"/>
    <transform from="\u{0308}u" to="ü"/>
    <transform from="\u{0301}y" to="ý"/>
    <transform from="\u{0308}y" to="ÿ"/>
    <transform from="\u{0304}A" to="Ā"/>
    <transform from="\u{0304}a" to="ā"/>
    <transform from="\u{0306}A" to="Ă"/>
    <transform from="\u{0306}a" to="ă"/>
    <transform from="\u{0301}C" to="Ć"/>
    <transform from="\u{0301}c" to="ć"/>
    <transform from="\u{0302}C" to="Ĉ"/>
    <transform from="\u{0302}c" to="ĉ"/>
    <transform from="\u{030c}C" to="Č"/>
    <transform from="\u{030c}c" to="č"/>
    <transform from="\u{030c}D" to="Ď"/>
    <transform from="\u{030c}d" to="ď"/>
    <transform from="\u{0304}E" to="Ē"/>
    <transform from="\u{0304}e" to="ē"/>
    <transform from="\u{0306}E" to="Ĕ"/>
    <transform from="\u{0306}e" to="ĕ"/>
    <transform from="\u{030c}E" to="Ě"/>
    <transform from="\u{030c}e" to="ě"/>
    <transform from="\u{0302}G" to="Ĝ"/>
    <transform from="\u{0302}g" to="ĝ"/>
    <transform from="\u{0306}G" to="Ğ"/>
    <transform from="\u{0306}g" to="ğ"/>
    <transform from="\u{0327}G" to="Ģ"/>
    <transform from="\u{0327}g" to="ģ"/>
    <transform from="\u{0302}H" to="Ĥ"/>
    <transform from="\u{0302}h" to="ĥ"/>
    <transform from="\u{0303}I" to="Ĩ"/>
    <transform from="\u{0303}i" to="ĩ"/>
    <transform from="\u{0304}I" to="Ī"/>
    <transform from="\u{0304}i" to="ī"/>
    <transform from="\u{0306}I" to="Ĭ"/>
    <transform from="\u{0306}i" to="ĭ"/>
    <transform from="\u{0302}J" to="Ĵ"/>
    <transform from="\u{0302}j" to="ĵ"/>
    <transform from="\u{0327}K" to="Ķ"/>
    <transform from="\u{0327}k" to="ķ"/>
    <transform from="\u{0301}L" to="Ĺ"/>
    <transform from="\u{0301}l" to="ĺ"/>
    <transform from="\u{0327}L" to="Ļ"/>
    <transform from="\u{0327}l" to="ļ"/>
    <transform from="\u{030c}L" to="Ľ"/>
    <transform from="\u{030c}l" to="ľ"/>
    <transform from="\u{0301}N" to="Ń"/>
    <transform from="\u{0301}n" to="ń"/>
    <transform from="\u{0327}N" to="Ņ"/>
    <transform from="\u{0327}n" to="ņ"/>
    <transform from="\u{030c}N" to="Ň"/>
    <transform from="\u{030c}n" to="ň"/>
    <transform from="\u{0304}O" to="Ō"/>
    <transform from="\u{0304}o" to="ō"/>
    <transform from="\u{0306}O" to="Ŏ"/>
    <transform from="\u{0306}o" to="ŏ"/>
    <transform from="\u{0301}R" to="Ŕ"/>
    <transform from="\u{0301}r" to="ŕ"/>
    <transform from="\u{0327}R" to="Ŗ"/>
    <transform from="\u{0327}r" to="ŗ"/>
    <transform from="\u{030c}R" to="Ř"/>
    <transform from="\u{030c}r" to="ř"/>
    <transform from="\u{0301}S" to="Ś"/>
    <transform from="\u{0301}s" to="ś"/>
    <transform from="\u{0302}S" to="Ŝ"/>
    <transform from="\u{0302}s" to="ŝ"/>
    <transform from="\u{0327}S" to="Ş"/>
    <transform from="\u{0327}s" to="ş"/>
    <transform from="\u{030c}S" to="Š"/>
    <transform from="\u{030c}s" to="š"/>
    <transform from="\u{0327}T" to="Ţ"/>
    <transform from="\u{0327}t" to="ţ"/>
    <transform from="\u{030c}T" to="Ť"/>
    <transform from="\u{030c}t" to="ť"/>
    <transform from="\u{0303}U" to="Ũ"/>
    <transform from="\u{0303}u" to="ũ"/>
    <transform from="\u{0304}U" to="Ū"/>
    <transform from="\u{0304}u" to="ū"/>
    <transform from="\u{0306}U" to="Ŭ"/>
    <transform from="\u{0306}u" to="ŭ"/>
    <transform from="\u{030a}U" to="Ů"/>
    <transform from="\u{030a}u" to="ů"/>
    <transform from="\u{0302}W" to="Ŵ"/>
    <transform from="\u{0302}w" to="ŵ"/>
    <transform from="\u{0302}Y" to="Ŷ"/>
    <transform from="\u{0302}y" to="ŷ"/>
    <transform from="\u{0308}Y" to="Ÿ"/>
    <transform from="\u{0301}Z" to="Ź"/>
    <transform from="\u{0301}z" to="ź"/>
    <transform from="\u{030c}Z" to="Ž"/>
    <transform from="\u{030c}z" to="ž"/>
    <transform from="\u{030c}A" to="Ǎ"/>
    <transform from="\u{030c}a" to="ǎ"/>
    <transform from="\u{030c}I" to="Ǐ"/>
    <transform from="\u{030c}i" to="ǐ"/>
    <transform from="\u{030c}O" to="Ǒ"/>
    <transform from="\u{030c}o" to="ǒ"/>
    <transform from="\u{030c}U" to="Ǔ"/>
    <transform from="\u{030c}u" to="ǔ"/>
    <transform from="\u{0304}\u{0308}U" to="Ǖ"/>
    <transform from="\u{0304}\u{0308}u" to="ǖ"/>
    <transform from="\u{0301}\u{0308}U" to="Ǘ"/>
    <transform from="\u{0301}\u{0308}u" to="ǘ"/>
    <transform from="\u{030c}\u{0308}U" to="Ǚ"/>
    <transform from="\u{030c}\u{0308}u" to="ǚ"/>
    <transform from="\u{0300}\u{0308}U" to="Ǜ"/>
    <transform from="\u{0300}\u{0308}u" to="ǜ"/>
    <transform from="\u{0304}\u{0308}A" to="Ǟ"/>
    <transform from="\u{0304}\u{0308}a" to="ǟ"/>
    <transform from="\u{030c}G" to="Ǧ"/>
    <transform from="\u{030c}g" to="ǧ"/>
    <transform from="\u{030c}K" to="Ǩ"/>
    <transform from="\u{030c}k" to="ǩ"/>
    <transform from="\u{030c}j" to="ǰ"/>
    <transform from="\u{0301}G" to="Ǵ"/>
    <transform from="\u{0301}g" to="ǵ"/>
    <transform from="\u{0300}N" to="Ǹ"/>
    <transform from="\u{0300}n" to="ǹ"/>
    <transform from="\u{0301}\u{030a}A" to="Ǻ"/>
    <transform from="\u{0301}\u{030a}a" to="ǻ"/>
    <transform from="\u{030c}H" to="Ȟ"/>
    <transform from="\u{030c}h" to="ȟ"/>
    <transform from="\u{0327}E" to="Ȩ"/>
    <transform from="\u{0327}e" to="ȩ"/>
    <transform from="\u{0304}\u{0308}O" to="Ȫ"/>
    <transform from="\u{0304}\u{0308}o" to="ȫ"/>
    <transform from="\u{0304}\u{0303}O" to="Ȭ"/>
    <transform from="\u{0304}\u{0303}o" to="ȭ"/>
    <transform from="\u{0304}Y" to="Ȳ"/>
    <transform from="\u{0304}y" to="ȳ"/>
    <transform from="\u{0308}´" to="̈́"/>
    <transform from="\u{0308}'" to="̈́"/>
    <transform from="\u{0301}\u{0308} " to="΅"/>
    <transform from="\u{0308}\u{0301} " to="΅"/>
    <transform from="\u{0301}Ω" to="Ώ"/>
    <transform from="\u{0301}\u{0327}C" to="Ḉ"/>
    <transform from="\u{0301}\u{0327}c" to="ḉ"/>
    <transform from="\u{0327}D" to="Ḑ"/>
    <transform from="\u{0327}d" to="ḑ"/>
    <transform from="\u{0300}\u{0304}E" to="Ḕ"/>
    <transform from="\u{0300}\u{0304}e" to="ḕ"/>
    <transform from="\u{0301}\u{0304}E" to="Ḗ"/>
    <transform from="\u{0301}\u{0304}e" to="ḗ"/>
    <transform from="\u{0306}\u{0327}E" to="Ḝ"/>
    <transform from="\u{0306}\u{0327}e" to="ḝ"/>
    <transform from="\u{0304}G" to="Ḡ"/>
    <transform from="\u{0304}g" to="ḡ"/>
    <transform from="\u{0308}H" to="Ḧ"/>
    <transform from="\u{0308}h" to="ḧ"/>
    <transform from="\u{0327}H" to="Ḩ"/>
    <transform from="\u{0327}h" to="ḩ"/>
    <transform from="\u{0301}\u{0308}I" to="Ḯ"/>
    <transform from="\u{0301}\u{0308}i" to="ḯ"/>
    <transform from="\u{0301}K" to="Ḱ"/>
    <transform from="\u{0301}k" to="ḱ"/>
    <transform from="\u{0301}M" to="Ḿ"/>
    <transform from="\u{0301}m" to="ḿ"/>
    <transform from="\u{0301}\u{0303}O" to="Ṍ"/>
    <transform from="\u{0301}\u{0303}o" to="ṍ"/>
    <transform from="\u{0308}\u{0303}O" to="Ṏ"/>
    <transform from="\u{0308}\u{0303}o" to="ṏ"/>
    <transform from="\u{0300}\u{0304}O" to="Ṑ"/>
    <transform from="\u{0300}\u{0304}o" to="ṑ"/>
    <transform from="\u{0301}\u{0304}O" to="Ṓ"/>
    <transform from="\u{0301}\u{0304}o" to="ṓ"/>
    <transform from="\u{0301}P" to="Ṕ"/>
    <transform from="\u{0301}p" to="ṕ"/>
    <transform from="\u{0301}\u{0303}U" to="Ṹ"/>
    <transform from="\u{0301}\u{0303}u" to="ṹ"/>
    <transform from="\u{0308}Ū" to="Ṻ"/>
    <transform from="\u{0308}\u{0304}U" to="Ṻ"/>
    <transform from="\u{0308}ū" to="ṻ"/>
    <transform from="\u{0308}\u{0304}u" to="ṻ"/>
    <transform from="\u{0303}V" to="Ṽ"/>
    <transform from="\u{0303}v" to="ṽ"/>
    <transform from="\u{0300}W" to="Ẁ"/>
    <transform from="\u{0300}w" to="ẁ"/>
    <transform from="\u{0301}W" to="Ẃ"/>
    <transform from="\u{0301}w" to="ẃ"/>
    <transform from="\u{0308}W" to="Ẅ"/>
    <transform from="\u{0308}w" to="ẅ"/>
    <transform from="\u{0308}X" to="Ẍ"/>
    <transform from="\u{0308}x" to="ẍ"/>
    <transform from="\u{0302}Z" to="Ẑ"/>
    <transform from="\u{0302}z" to="ẑ"/>
    <transform from="\u{0308}t" to="ẗ"/>
    <transform from="\u{030a}w" to="ẘ"/>
    <transform from="\u{030a}y" to="ẙ"/>
    <transform from="\u{0301}\u{0302}A" to="Ấ"/>
    <transform from="\u{0301}\u{0302}a" to="ấ"/>
    <transform from="\u{0300}\u{0302}A" to="Ầ"/>
    <transform from="\u{0300}\u{0302}a" to="ầ"/>
    <transform from="\u{0303}\u{0302}A" to="Ẫ"/>
    <transform from="\u{0303}\u{0302}a" to="ẫ"/>
    <transform from="\u{0301}\u{0306}A" to="Ắ"/>
    <transform from="\u{0301}\u{0306}a" to="ắ"/>
    <transform from="\u{0300}\u{0306}A" to="Ằ"/>
    <transform from="\u{0300}\u{0306}a" to="ằ"/>
    <transform from="\u{0303}\u{0306}A" to="Ẵ"/>
    <transform from="\u{0303}\u{0306}a" to="ẵ"/>
    <transform from="\u{0303}E" to="Ẽ"/>
    <transform from="\u{0303}e" to="ẽ"/>
    <transform from="\u{0301}\u{0302}E" to="Ế"/>
    <transform from="\u{0301}\u{0302}e" to="ế"/>
    <transform from="\u{0300}\u{0302}E" to="Ề"/>
    <transform from="\u{0300}\u{0302}e" to="ề"/>
    <transform from="\u{0303}\u{0302}E" to="Ễ"/>
    <transform from="\u{0303}\u{0302}e" to="ễ"/>
    <transform from="\u{0301}\u{0302}O" to="Ố"/>
    <transform from="\u{0301}\u{0302}o" to="ố"/>
    <transform from="\u{0300}\u{0302}O" to="Ồ"/>
    <transform from="\u{0300}\u{0302}o" to="ồ"/>
    <transform from="\u{0303}\u{0302}O" to="Ỗ"/>
    <transform from="\u{0303}\u{0302}o" to="ỗ"/>
    <transform from="\u{0300}Y" to="Ỳ"/>
    <transform from="\u{0300}y" to="ỳ"/>
    <transform from="\u{0303}Y" to="Ỹ"/>
    <transform from="\u{0303}y" to="ỹ"/>
    <transform from="\u{0300}Ω" to="Ὼ"/>
    <transform from="\u{0302}0" to="⁰"/>
    <transform from="\u{0302}4" to="⁴"/>
    <transform from="\u{0302}5" to="⁵"/>
    <transform from="\u{0302}6" to="⁶"/>
    <transform from="\u{0302}7" to="⁷"/>
    <transform from="\u{0302}8" to="⁸"/>
    <transform from="\u{0302}9" to="⁹"/>
    <transform from="\u{0302}+" to="⁺"/>
    <transform from="\u{0302}-" to="⁻"/>
    <transform from="\u{0302}−" to="⁻"/>
    <transform from="\u{0302}=" to="⁼"/>
    <transform from="\u{0302}(" to="⁽"/>
    <transform from="\u{0302})" to="⁾"/>
    <transform from="\u{0301}V" to="Ǘ"/>
    <transform from="\u{0301}v" to="ǘ"/>
    <transform from="\u{0301} " to="́"/>
    <transform from="\u{0306} " to="̆"/>
    <transform from="\u{030c}(" to="₍"/>
    <transform from="\u{030c})" to="₎"/>
    <transform from="\u{030c}+" to="₊"/>
    <transform from="\u{030c}-" to="₋"/>
    <transform from="\u{030c}0" to="₀"/>
    <transform from="\u{030c}1" to="₁"/>
    <transform from="\u{030c}2" to="₂"/>
    <transform from="\u{030c}3" to="₃"/>
    <transform from="\u{030c}4" to="₄"/>
    <transform from="\u{030c}5" to="₅"/>
    <transform from="\u{030c}6" to="₆"/>
    <transform from="\u{030c}7" to="₇"/>
    <transform from="\u{030c}8" to="₈"/>
    <transform from="\u{030c}9" to="₉"/>
    <transform from="\u{030c}=" to="₌"/>
    <transform from="\u{030c}V" to="Ǚ"/>
    <transform from="\u{030c}v" to="ǚ"/>
    <transform from="\u{030c} " to="̌"/>
    <transform from="\u{0327}¢" to="₵"/>
    <transform from="\u{0327} " to="̧"/>
    <transform from="\u{0302} " to="̂"/>
    <transform from="\u{0308} " to="̈"/>
    <transform from="\u{0300}V" to="Ǜ"/>
    <transform from="\u{0300}v" to="ǜ"/>
    <transform from="\u{0300} " to="̀"/>
    <transform from="\u{0304}V" to="Ǖ"/>
    <transform from="\u{0304}v" to="ǖ"/>
    <transform from="\u{0304} " to="̄"/>
    <transform from="\u{030a} " to="̊"/>
    <transform from="\u{0303}=" to="≃"/>
    <transform from="\u{0303}&lt;" to="≲"/>
    <transform from="\u{0303}&gt;" to="≳"/>
    <transform from="\u{0303} " to="̃"/>
    <transform from="\u{0306}\u{0301}A" to="Ắ"/>
    <transform from="\u{0306}\u{0301}a" to="ắ"/>
    <transform from="\u{0327}\u{0301}C" to="Ḉ"/>
    <transform from="\u{0327}\u{0301}c" to="ḉ"/>
    <transform from="\u{0302}\u{0301}A" to="Ấ"/>
    <transform from="\u{0302}\u{0301}a" to="ấ"/>
    <transform from="\u{0302}\u{0301}E" to="Ế"/>
    <transform from="\u{0302}\u{0301}e" to="ế"/>
    <transform from="\u{0302}\u{0301}O" to="Ố"/>
    <transform from="\u{0302}\u{0301}o" to="ố"/>
    <transform from="\u{0308}\u{0301}I" to="Ḯ"/>
    <transform from="\u{0308}\u{0301}i" to="ḯ"/>
    <transform from="\u{0308}\u{0301}U" to="Ǘ"/>
    <transform from="\u{0308}\u{0301}u" to="ǘ"/>
    <transform from="\u{0304}\u{0301}E" to="Ḗ"/>
    <transform from="\u{0304}\u{0301}e" to="ḗ"/>
    <transform from="\u{0304}\u{0301}O" to="Ṓ"/>
    <transform from="\u{0304}\u{0301}o" to="ṓ"/>
    <transform from="\u{030a}\u{0301}A" to="Ǻ"/>
    <transform from="\u{030a}\u{0301}a" to="ǻ"/>
    <transform from="\u{0303}\u{0301}O" to="Ṍ"/>
    <transform from="\u{0303}\u{0301}o" to="ṍ"/>
    <transform from="\u{0303}\u{0301}U" to="Ṹ"/>
    <transform from="\u{0303}\u{0301}u" to="ṹ"/>
    <transform from="\u{0327}\u{0306}E" to="Ḝ"/>
    <transform from="\u{0327}\u{0306}e" to="ḝ"/>
    <transform from="\u{0306}\u{0300}A" to="Ằ"/>
    <transform from="\u{0306}\u{0300}a" to="ằ"/>
    <transform from="\u{0306}\u{0303}A" to="Ẵ"/>
    <transform from="\u{0306}\u{0303}a" to="ẵ"/>
    <transform from="\u{0308}\u{030c}U" to="Ǚ"/>
    <transform from="\u{0308}\u{030c}u" to="ǚ"/>
    <transform from="\u{0302}\u{0300}A" to="Ầ"/>
    <transform from="\u{0302}\u{0300}a" to="ầ"/>
    <transform from="\u{0302}\u{0300}E" to="Ề"/>
    <transform from="\u{0302}\u{0300}e" to="ề"/>
    <transform from="\u{0302}\u{0300}O" to="Ồ"/>
    <transform from="\u{0302}\u{0300}o" to="ồ"/>
    <transform from="\u{0302}\u{0303}A" to="Ẫ"/>
    <transform from="\u{0302}\u{0303}a" to="ẫ"/>
    <transform from="\u{0302}\u{0303}E" to="Ễ"/>
    <transform from="\u{0302}\u{0303}e" to="ễ"/>
    <transform from="\u{0302}\u{0303}O" to="Ỗ"/>
    <transform from="\u{0302}\u{0303}o" to="ỗ"/>
    <transform from="\u{0308}\u{0300}U" to="Ǜ"/>
    <transform from="\u{0308}\u{0300}u" to="ǜ"/>
    <transform from="\u{0308}\u{0304}A" to="Ǟ"/>
    <transform from="\u{0308}\u{0304}a" to="ǟ"/>
    <transform from="\u{0308}\u{0304}O" to="Ȫ"/>
    <transform from="\u{0308}\u{0304}o" to="ȫ"/>
    <transform from="\u{0303}\u{0308}O" to="Ṏ"/>
    <transform from="\u{0303}\u{0308}o" to="ṏ"/>
    <transform from="\u{0304}\u{0300}E" to="Ḕ"/>
    <transform from="\u{0304}\u{0300}e" to="ḕ"/>
    <transform from="\u{0304}\u{0300}O" to="Ṑ"/>
    <transform from="\u{0304}\u{0300}o" to="ṑ"/>
    <transform from="\u{0303}\u{0304}O" to="Ȭ"/>
    <transform from="\u{0303}\u{0304}o" to="ȭ"/>
    <transform from="\u{0301}\u{0303}a" to="a"/>
    <transform from="\u{0300}\u{0303}a" to="a"/>
    <transform from="\u{0301}\u{0303}A" to="A"/>
    <transform from="\u{0300}\u{0303}A" to="A"/>
    <transform from="\u{0301}\u{0303}e" to="e"/>
    <transform from="\u{0300}\u{0303}e" to="e"/>
    <transform from="\u{0301}\u{0303}E" to="E"/>
    <transform from="\u{0300}\u{0303}E" to="E"/>
    <transform from="\u{0301}\u{0303}i" to="i"/>
    <transform from="\u{0300}\u{0303}i" to="i"/>
    <transform from="\u{0301}\u{0303}I" to="I"/>
    <transform from="\u{0300}\u{0303}I" to="I"/>
    <transform from="\u{0300}\u{0303}o" to="o"/>
    <transform from="\u{0300}\u{0303}O" to="O"/>
    <transform from="\u{0300}\u{0303}u" to="u"/>
    <transform from="\u{0300}\u{0303}U" to="U"/>
    <transform from="\u{0300}m" to="m"/>
    <transform from="\u{0300}M" to="M"/>
  </transforms>
</keyboard>

