<!DOCTYPE keyboard SYSTEM "../dtd/ldmlKeyboard.dtd">
<keyboard locale="pa-t-k0-linux-a1872e33">
  <version platform="0" number="$Revision$"/>
  <names>
    <name value="Punjabi (Gurmukhi)"/>
    <name value="in(guru)"/>
  </names>
  <settings transformFailure="omit" transformPartial="hide"/>
  <keyMap>
    <map iso="E01" to="੧"/>
    <map iso="E02" to="੨"/>
    <map iso="E03" to="੩"/>
    <map iso="E04" to="੪"/>
    <map iso="E05" to="੫"/>
    <map iso="E06" to="੬"/>
    <map iso="E07" to="੭"/>
    <map iso="E08" to="੮"/>
    <map iso="E09" to="੯"/>
    <map iso="E10" to="੦"/>
    <map iso="E11" to="ਃ"/>
    <map iso="E12" to="="/>
    <map iso="D01" to="ੌ"/>
    <map iso="D02" to="ੈ"/>
    <map iso="D03" to="ਾ"/>
    <map iso="D04" to="ੀ"/>
    <map iso="D05" to="ੂ"/>
    <map iso="D06" to="ਬ"/>
    <map iso="D07" to="ਹ"/>
    <map iso="D08" to="ਗ"/>
    <map iso="D09" to="ਦ"/>
    <map iso="D10" to="ਜ"/>
    <map iso="D11" to="ਡ"/>
    <map iso="D12" to="਼"/>
    <map iso="C01" to="ੋ"/>
    <map iso="C02" to="ੇ"/>
    <map iso="C03" to="੍"/>
    <map iso="C04" to="ਿ"/>
    <map iso="C05" to="ੁ"/>
    <map iso="C06" to="ਪ"/>
    <map iso="C07" to="ਰ"/>
    <map iso="C08" to="ਕ"/>
    <map iso="C09" to="ਤ"/>
    <map iso="C10" to="ਚ"/>
    <map iso="C11" to="ਟ"/>
    <map iso="C12" to="\"/>
    <map iso="B00" to="&lt;"/>
    <map iso="B01" to="z"/>
    <map iso="B02" to="ਂ"/>
    <map iso="B03" to="ਮ"/>
    <map iso="B04" to="ਨ"/>
    <map iso="B05" to="ਵ"/>
    <map iso="B06" to="ਲ"/>
    <map iso="B07" to="ਸ"/>
    <map iso="B08" to=","/>
    <map iso="B09" to="."/>
    <map iso="B10" to="ਯ"/>
    <map iso="A03" to=" "/>
  </keyMap>
  <keyMap modifiers="shift">
    <map iso="E01" to="੧"/>
    <map iso="E02" to="੨"/>
    <map iso="E03" to="ੱ"/>
    <map iso="E04" to="ੴ"/>
    <map iso="E05" to="☬"/>
    <map iso="E06" to="੬"/>
    <map iso="E07" to="੭"/>
    <map iso="E08" to="੮"/>
    <map iso="E09" to="("/>
    <map iso="E10" to=")"/>
    <map iso="E11" to="ਃ"/>
    <map iso="E12" to="+"/>
    <map iso="D01" to="ਔ"/>
    <map iso="D02" to="ਐ"/>
    <map iso="D03" to="ਆ"/>
    <map iso="D04" to="ਈ"/>
    <map iso="D05" to="ਊ"/>
    <map iso="D06" to="ਭ"/>
    <map iso="D07" to="ਙ"/>
    <map iso="D08" to="ਘ"/>
    <map iso="D09" to="ਧ"/>
    <map iso="D10" to="ਝ"/>
    <map iso="D11" to="ਢ"/>
    <map iso="D12" to="ਞ"/>
    <map iso="C01" to="ਓ"/>
    <map iso="C02" to="ਏ"/>
    <map iso="C03" to="ਅ"/>
    <map iso="C04" to="ਇ"/>
    <map iso="C05" to="ਉ"/>
    <map iso="C06" to="ਫ"/>
    <map iso="C07" to="ੜ"/>
    <map iso="C08" to="ਖ"/>
    <map iso="C09" to="ਥ"/>
    <map iso="C10" to="ਛ"/>
    <map iso="C11" to="ਠ"/>
    <map iso="C12" to="|"/>
    <map iso="B00" to="&gt;"/>
    <map iso="B01" to="ਁ"/>
    <map iso="B02" to="ੰ"/>
    <map iso="B03" to="ਣ"/>
    <map iso="B04" to="ਨ"/>
    <map iso="B05" to="ਵ"/>
    <map iso="B06" to="ਲ਼"/>
    <map iso="B07" to="ਸ਼"/>
    <map iso="B08" to="&lt;"/>
    <map iso="B09" to="।"/>
    <map iso="B10" to="?"/>
    <map iso="A03" to=" "/>
  </keyMap>
  <keyMap modifiers="ctrl+alt">
    <map iso="E01" to="੧"/>
    <map iso="E02" to="੨"/>
    <map iso="E03" to="੩"/>
    <map iso="E04" to="₹"/>
    <map iso="E05" to="੫"/>
    <map iso="E06" to="੬"/>
    <map iso="E07" to="੭"/>
    <map iso="E08" to="੮"/>
    <map iso="E09" to="੯"/>
    <map iso="E10" to="੦"/>
    <map iso="E11" to="ਃ"/>
    <map iso="E12" to="="/>
    <map iso="D01" to="ੌ"/>
    <map iso="D02" to="ੈ"/>
    <map iso="D03" to="ਾ"/>
    <map iso="D04" to="ੀ"/>
    <map iso="D05" to="ੂ"/>
    <map iso="D06" to="ਬ"/>
    <map iso="D07" to="ਹ"/>
    <map iso="D08" to="ਗ"/>
    <map iso="D09" to="ਦ"/>
    <map iso="D10" to="ਜ"/>
    <map iso="D11" to="ਡ"/>
    <map iso="D12" to="਼"/>
    <map iso="C01" to="ੋ"/>
    <map iso="C02" to="ੇ"/>
    <map iso="C03" to="੍"/>
    <map iso="C04" to="ਿ"/>
    <map iso="C05" to="ੁ"/>
    <map iso="C06" to="ਪ"/>
    <map iso="C07" to="ਰ"/>
    <map iso="C08" to="ਕ"/>
    <map iso="C09" to="ਤ"/>
    <map iso="C10" to="ਚ"/>
    <map iso="C11" to="ਟ"/>
    <map iso="C12" to="\"/>
    <map iso="B00" to="|"/>
    <map iso="B01" to="z"/>
    <map iso="B02" to="ੱ"/>
    <map iso="B03" to="ਮ"/>
    <map iso="B04" to="ਨ"/>
    <map iso="B05" to="ਵ"/>
    <map iso="B06" to="ਲ"/>
    <map iso="B07" to="ਸ"/>
    <map iso="B08" to=","/>
    <map iso="B09" to="."/>
    <map iso="B10" to="ਯ"/>
    <map iso="A03" to=" "/>
  </keyMap>
  <keyMap modifiers="ctrl+alt+shift">
    <map iso="E01" to="੧"/>
    <map iso="E02" to="੨"/>
    <map iso="E03" to="ੱ"/>
    <map iso="E05" to="☬"/>
    <map iso="E06" to="੬"/>
    <map iso="E07" to="੭"/>
    <map iso="E08" to="੮"/>
    <map iso="E09" to="("/>
    <map iso="E10" to=")"/>
    <map iso="E11" to="ਃ"/>
    <map iso="E12" to="+"/>
    <map iso="D01" to="ਔ"/>
    <map iso="D02" to="ਐ"/>
    <map iso="D03" to="ਆ"/>
    <map iso="D04" to="ਈ"/>
    <map iso="D05" to="ਊ"/>
    <map iso="D06" to="ਭ"/>
    <map iso="D07" to="ਙ"/>
    <map iso="D08" to="ਘ"/>
    <map iso="D09" to="ਧ"/>
    <map iso="D10" to="ਝ"/>
    <map iso="D11" to="ਢ"/>
    <map iso="D12" to="ਞ"/>
    <map iso="C01" to="ਓ"/>
    <map iso="C02" to="ਏ"/>
    <map iso="C03" to="ਅ"/>
    <map iso="C04" to="ਇ"/>
    <map iso="C05" to="ਉ"/>
    <map iso="C06" to="ਫ"/>
    <map iso="C07" to="ੜ"/>
    <map iso="C08" to="ਖ"/>
    <map iso="C09" to="ਥ"/>
    <map iso="C10" to="ਛ"/>
    <map iso="C11" to="ਠ"/>
    <map iso="C12" to="|"/>
    <map iso="B00" to="¦"/>
    <map iso="B01" to="ਁ"/>
    <map iso="B03" to="ਣ"/>
    <map iso="B04" to="ਨ"/>
    <map iso="B05" to="ਵ"/>
    <map iso="B06" to="ਲ਼"/>
    <map iso="B07" to="ਸ਼"/>
    <map iso="B08" to="&lt;"/>
    <map iso="B09" to="।"/>
    <map iso="B10" to="?"/>
    <map iso="A03" to=" "/>
  </keyMap>
</keyboard>

